[
    {
        "serverList": [
            "nbonros02.traiteur.fr.bonduelle.com",
            "nbonros03.traiteur.fr.bonduelle.com",
            "nbonros13.traiteur.fr.bonduelle.com",
            "nbonros12.traiteur.fr.bonduelle.com"
        ],
        "softname": "Adobe Reader"
    },
    {
        "serverList": [
            "WISTR20",
            "WKFR02789",
            "srbonmr12.adellego.com",
            "WKFR03264",
            "WKFR04495",
            "ip-10-3-102-127.eu-west-1.compute.internal",
            "ip-10-3-102-152.eu-west-1.compute.internal",
            "WKFR04704",
            "ip-10-3-99-140.eu-west-1.compute.internal",
            "WKFR05000",
            "ip-10-3-99-136.eu-west-1.compute.internal",
            "WKFR03263",
            "ip-10-3-99-138.eu-west-1.compute.internal",
            "WKFRVAUPCTSP0",
            "ip-10-3-99-119.eu-west-1.compute.internal",
            "WKFR05050",
            "WKFR02201",
            "WKFR02948",
            "WKFR04492",
            "WKFR02437",
            "WKFR01443",
            "WKFR00482",
            "WKFR00514",
            "ip-10-0-8-42.eu-west-1.compute.internal",
            "ip-10-0-8-20.eu-west-1.compute.internal",
            "ip-10-0-9-70.eu-west-1.compute.internal",
            "056C301",
            "056FPBM1",
            "056F40T1",
            "056F201",
            "WKFR01864"
        ],
        "softname": "Adobe Acrobat Reader"
    },
    {
        "serverList": [
            "WKFR04495",
            "ip-10-3-102-152.eu-west-1.compute.internal",
            "WKFR02201",
            "WKFR04492",
            "WKFR01443",
            "WKFR00482",
            "WKFR00514",
            "056C301",
            "056FPBM1",
            "nbonros02.traiteur.fr.bonduelle.com",
            "nbonros03.traiteur.fr.bonduelle.com"
        ],
        "softname": "Adobe PDF Reader"
    },
    {
        "serverList": [
            "WKFR02789",
            "WKFR03264",
            "WKFR04495",
            "ip-10-3-102-127.eu-west-1.compute.internal",
            "ip-10-3-102-152.eu-west-1.compute.internal",
            "WKFR04704",
            "ip-10-3-99-140.eu-west-1.compute.internal",
            "WKFR05000",
            "ip-10-3-99-136.eu-west-1.compute.internal",
            "WKFR03263",
            "ip-10-3-99-138.eu-west-1.compute.internal",
            "WKFRVAUPCTSP0",
            "ip-10-3-99-119.eu-west-1.compute.internal",
            "WKFR02981",
            "WKFR05050",
            "WKFR02201",
            "WKFR03017",
            "WKFR02948",
            "WKFR04492",
            "WKFR02437",
            "WKFR01443",
            "WKFR00482",
            "WKFR00514",
            "ip-10-0-8-42.eu-west-1.compute.internal",
            "ip-10-0-8-20.eu-west-1.compute.internal",
            "ip-10-0-9-70.eu-west-1.compute.internal",
            "WKFR01864"
        ],
        "softname": "Adobe AIR"
    },
    {
        "serverList": [
            "ip-192-168-242-11.eu-west-1.compute.internal",
            "ip-192-168-242-11.eu-west-1.compute.internal",
            "WKFR02789",
            "WKFR02789",
            "srbonmr12.adellego.com",
            "WKFR03264",
            "WKFR02460",
            "WKFR04495",
            "ip-10-3-102-127.eu-west-1.compute.internal",
            "ip-10-3-102-152.eu-west-1.compute.internal",
            "WKFR04704",
            "WKFR04704",
            "ip-10-3-102-137.eu-west-1.compute.internal",
            "ip-10-3-99-140.eu-west-1.compute.internal",
            "ip-10-3-102-67.eu-west-1.compute.internal",
            "WKFR05000",
            "ip-10-3-99-136.eu-west-1.compute.internal",
            "WKFR03263",
            "ip-10-3-99-138.eu-west-1.compute.internal",
            "WKFRVAUPCTSP0",
            "ip-10-3-99-119.eu-west-1.compute.internal",
            "WKFR05050",
            "WKFR02201",
            "WKFR02948",
            "WKFR04492",
            "WKFR02437",
            "WKFR02480",
            "WKFR01443",
            "WKFR01443",
            "WKFR00482",
            "WKFR00514",
            "ip-10-0-8-42.eu-west-1.compute.internal",
            "ip-10-0-8-20.eu-west-1.compute.internal",
            "ip-10-0-9-70.eu-west-1.compute.internal",
            "WKFR01864",
            "WKFR01864",
            "nbonros13.traiteur.fr.bonduelle.com",
            "nbonros12.traiteur.fr.bonduelle.com"
        ],
        "softname": "Adobe Flash"
    },
    {
        "serverList": [
            "WKFRVAUPCTSP0",
            "WKFRVAUPCTSP0"
        ],
        "softname": "LogMeIn"
    },
    {
        "serverList": [
            "WISTR20",
            "WKFR02789",
            "ip-192-168-242-115.eu-west-1.compute.internal",
            "WKFR03264",
            "WKFR04495",
            "ip-10-3-102-127.eu-west-1.compute.internal",
            "ip-10-3-102-152.eu-west-1.compute.internal",
            "WKFR04704",
            "WKFR05000",
            "ip-10-3-99-136.eu-west-1.compute.internal",
            "WKFR03263",
            "ip-10-3-99-138.eu-west-1.compute.internal",
            "WKFRVAUPCTSP0",
            "ip-10-3-99-119.eu-west-1.compute.internal",
            "WKFR05050",
            "WKFR02201",
            "WKFR02948",
            "WKFR04492",
            "WKFR02437",
            "WKFR01443",
            "WKFR00482",
            "WKFR00514",
            "ip-10-0-8-42.eu-west-1.compute.internal",
            "ip-10-0-8-20.eu-west-1.compute.internal",
            "ip-10-0-9-70.eu-west-1.compute.internal",
            "WKFR01864",
            "nbonros03.traiteur.fr.bonduelle.com"
        ],
        "softname": "Microsoft Office"
    },
    {
        "serverList": [
            "wistr24.adellego.com",
            "ip-192-168-242-29.eu-west-1.compute.internal",
            "ip-192-168-242-11.eu-west-1.compute.internal",
            "ip-192-168-242-11.eu-west-1.compute.internal",
            "wistr22.adellego.com",
            "wistr23.adellego.com",
            "wistr23.adellego.com",
            "WISTR20",
            "wiein001.adellego.com",
            "wistr06",
            "WKFR02789",
            "srbonmr12.adellego.com",
            "srbonmr12.adellego.com",
            "WKFR03264",
            "WKFR04495",
            "WKFR04495",
            "ip-10-3-102-127.eu-west-1.compute.internal",
            "ip-10-3-102-152.eu-west-1.compute.internal",
            "ip-10-3-102-152.eu-west-1.compute.internal",
            "WKFR04704",
            "ip-10-3-99-140.eu-west-1.compute.internal",
            "WKFR05000",
            "ip-10-3-99-136.eu-west-1.compute.internal",
            "WKFR03263",
            "ip-10-3-99-138.eu-west-1.compute.internal",
            "WKFRVAUPCTSP0",
            "ip-10-3-99-119.eu-west-1.compute.internal",
            "WKFR05050",
            "WKFR02201",
            "WKFR02201",
            "WKFR02948",
            "WKFR04492",
            "WKFR04492",
            "WKFR02437",
            "WKFR01443",
            "WKFR01443",
            "WKFR00482",
            "WKFR00482",
            "WKFR00514",
            "ip-10-0-8-42.eu-west-1.compute.internal",
            "ip-10-0-8-20.eu-west-1.compute.internal",
            "ip-10-0-9-70.eu-west-1.compute.internal",
            "056C301",
            "056C301",
            "056FPBM1",
            "056F40T1",
            "056F201",
            "WKFR01864"
        ],
        "softname": "Silverlight"
    },
    {
        "serverList": [
            "DCVDA001.ADELLEGO.COM",
            "wiein001.adellego.com",
            "srbonmr12.adellego.com"
        ],
        "softname": "Mozilla Firefox"
    },
    {
        "serverList": [
            "WKFR02789",
            "WKFR02789",
            "WKFR06170",
            "WKFR06170",
            "WKFR03264",
            "WKFR03264",
            "WKFR02460",
            "WKFR02460",
            "WKFR04495",
            "WKFR04495",
            "ip-10-3-102-127.eu-west-1.compute.internal",
            "ip-10-3-102-127.eu-west-1.compute.internal",
            "ip-10-3-102-152.eu-west-1.compute.internal",
            "ip-10-3-102-152.eu-west-1.compute.internal",
            "WKFR04704",
            "WKFR04704",
            "ip-10-3-102-137.eu-west-1.compute.internal",
            "ip-10-3-102-137.eu-west-1.compute.internal",
            "ip-10-3-99-140.eu-west-1.compute.internal",
            "ip-10-3-99-140.eu-west-1.compute.internal",
            "ip-10-3-102-67.eu-west-1.compute.internal",
            "ip-10-3-102-67.eu-west-1.compute.internal",
            "WKFR05000",
            "WKFR05000",
            "ip-10-3-99-136.eu-west-1.compute.internal",
            "ip-10-3-99-136.eu-west-1.compute.internal",
            "WKFR03263",
            "WKFR03263",
            "ip-10-3-99-138.eu-west-1.compute.internal",
            "ip-10-3-99-138.eu-west-1.compute.internal",
            "WKFRVAUPCTSP0",
            "WKFRVAUPCTSP0",
            "ip-10-3-99-119.eu-west-1.compute.internal",
            "ip-10-3-99-119.eu-west-1.compute.internal",
            "WKFR02981",
            "WKFR02981",
            "WKFR05050",
            "WKFR05050",
            "WKFR02201",
            "WKFR02201",
            "WKFR03017",
            "WKFR03017",
            "WKFR02948",
            "WKFR02948",
            "WKFR04492",
            "WKFR04492",
            "WKFR02437",
            "WKFR02437",
            "WKFR02480",
            "WKFR02480",
            "WKFR01443",
            "WKFR01443",
            "WKFR00482",
            "WKFR00482",
            "WKFR00514",
            "WKFR00514",
            "ip-10-0-8-42.eu-west-1.compute.internal",
            "ip-10-0-8-42.eu-west-1.compute.internal",
            "ip-10-0-8-20.eu-west-1.compute.internal",
            "ip-10-0-8-20.eu-west-1.compute.internal",
            "ip-10-0-9-70.eu-west-1.compute.internal",
            "ip-10-0-9-70.eu-west-1.compute.internal",
            "056C301",
            "056C301",
            "056FPBM1",
            "056FPBM1",
            "056F40T1",
            "056F40T1",
            "056F201",
            "056F201",
            "WKFR01864",
            "WKFR01864"
        ],
        "softname": "TeamViewer"
    },
    {
        "serverList": [
            "WKFR02789",
            "WKFR03264",
            "WKFR04495",
            "ip-10-3-102-127.eu-west-1.compute.internal",
            "ip-10-3-102-152.eu-west-1.compute.internal",
            "WKFR04704",
            "ip-10-3-99-140.eu-west-1.compute.internal",
            "WKFR05000",
            "ip-10-3-99-136.eu-west-1.compute.internal",
            "WKFR03263",
            "ip-10-3-99-138.eu-west-1.compute.internal",
            "WKFRVAUPCTSP0",
            "ip-10-3-99-119.eu-west-1.compute.internal",
            "WKFR05050",
            "WKFR02201",
            "WKFR02948",
            "WKFR04492",
            "WKFR02437",
            "WKFR01443",
            "WKFR00482",
            "WKFR00514",
            "ip-10-0-8-42.eu-west-1.compute.internal",
            "ip-10-0-8-20.eu-west-1.compute.internal",
            "ip-10-0-9-70.eu-west-1.compute.internal",
            "WKFR01864"
        ],
        "softname": "VideoLAN"
    },
    {
        "serverList": [
            "DCPRD001.ADELLEGO.COM"
        ],
        "softname": "Wireshark"
    }
]